Metadata-Version: 1.0
Name: udac-dist
Version: 0.1
Summary: Gaussian distributions
Home-page: UNKNOWN
Author: James Lau
Author-email: jimbo_lau@yahoo.com
License: UNKNOWN
Platform: UNKNOWN
